odoo/addons/l10n_br_account/README.rst
odoo/addons/l10n_br_account/__init__.py
odoo/addons/l10n_br_account/__manifest__.py
odoo/addons/l10n_br_account/hooks.py
odoo/addons/l10n_br_account/data/account_tax_group.xml
odoo/addons/l10n_br_account/data/account_tax_template.xml
odoo/addons/l10n_br_account/demo/res_users_demo.xml
odoo/addons/l10n_br_account/i18n/l10n_br_account.pot
odoo/addons/l10n_br_account/i18n/pt_BR.po
odoo/addons/l10n_br_account/images/l10n_br-hover.png
odoo/addons/l10n_br_account/images/l10n_br.png
odoo/addons/l10n_br_account/migrations/12.0.4.0.0/pre-migration.py
odoo/addons/l10n_br_account/migrations/12.0.7.0.0/pre-migration.py
odoo/addons/l10n_br_account/migrations/8.0.1.0.1/openupgrade_analysis.txt
odoo/addons/l10n_br_account/migrations/8.0.1.0.1/openupgrade_analysis_work.txt
odoo/addons/l10n_br_account/models/__init__.py
odoo/addons/l10n_br_account/models/account_document_line_mixin.py
odoo/addons/l10n_br_account/models/account_incoterms.py
odoo/addons/l10n_br_account/models/account_invoice.py
odoo/addons/l10n_br_account/models/account_invoice_line.py
odoo/addons/l10n_br_account/models/account_journal.py
odoo/addons/l10n_br_account/models/account_move.py
odoo/addons/l10n_br_account/models/account_tax.py
odoo/addons/l10n_br_account/models/account_tax_group.py
odoo/addons/l10n_br_account/models/account_tax_template.py
odoo/addons/l10n_br_account/models/fiscal_document.py
odoo/addons/l10n_br_account/models/fiscal_document_line.py
odoo/addons/l10n_br_account/models/fiscal_operation.py
odoo/addons/l10n_br_account/models/fiscal_operation_line.py
odoo/addons/l10n_br_account/models/fiscal_tax.py
odoo/addons/l10n_br_account/models/fiscal_tax_group.py
odoo/addons/l10n_br_account/models/res_company.py
odoo/addons/l10n_br_account/readme/CONFIGURE.rst
odoo/addons/l10n_br_account/readme/CONTRIBUTORS.rst
odoo/addons/l10n_br_account/readme/DESCRIPTION.rst
odoo/addons/l10n_br_account/readme/HISTORY.rst
odoo/addons/l10n_br_account/readme/INSTALL.rst
odoo12_addon_l10n_br_account-12.0.16.4.0.dist-info/METADATA
odoo12_addon_l10n_br_account-12.0.16.4.0.dist-info/WHEEL
odoo12_addon_l10n_br_account-12.0.16.4.0.dist-info/top_level.txt
odoo12_addon_l10n_br_account-12.0.16.4.0.dist-info/RECORD
