Metadata-Version: 2.1
Name: odoo12-addon-l10n_br_account
Version: 12.0.16.4.0
Summary: Brazilian Localization Account
Home-page: https://github.com/OCA/l10n-brazil
Author: Akretion, Odoo Community Association (OCA)
Author-email: support@odoo-community.org
License: AGPL-3
Classifier: Programming Language :: Python
Classifier: Framework :: Odoo
Classifier: Framework :: Odoo :: 12.0
Classifier: License :: OSI Approved :: GNU Affero General Public License v3
Classifier: Development Status :: 4 - Beta
Requires-Python: >=3.5
Requires-Dist: odoo12-addon-l10n-br-account-due-list
Requires-Dist: odoo12-addon-l10n-br-coa
Requires-Dist: odoo12-addon-l10n-br-fiscal
Requires-Dist: odoo <12.1dev,>=12.0a
